PKK/V12.py
PKK/__init__.py
PKK-0.2.dist-info/LICENSE
PKK-0.2.dist-info/METADATA
PKK-0.2.dist-info/WHEEL
PKK-0.2.dist-info/top_level.txt
PKK-0.2.dist-info/RECORD
